jami_commander/__init__.py
jami_commander/jami_commander.py
jami_commander/controller/__init__.py
jami_commander/controller/controller.py
jami_commander/controller/errorsDring.py
jami_commander-0.8.0.dist-info/LICENSE
jami_commander-0.8.0.dist-info/METADATA
jami_commander-0.8.0.dist-info/WHEEL
jami_commander-0.8.0.dist-info/entry_points.txt
jami_commander-0.8.0.dist-info/top_level.txt
jami_commander-0.8.0.dist-info/RECORD
