Metadata-Version: 2.1
Name: jami-commander
Version: 0.8.0
Summary: A simple command-line Jami (jami.net) client
Home-page: https://github.com/8go/jami-commander
Author: 8go
Project-URL: Bug Tracker, https://github.com/8go/jami-commander/issues
Project-URL: repository, https://github.com/8go/jami-commander
Keywords: Jami,chat,messaging,CLI
Classifier: Programming Language :: Python :: 3.11
Classifier: Programming Language :: Python :: 3.12
Classifier: License :: OSI Approved :: GNU Lesser General Public License v3 or later (LGPLv3+)
Classifier: Operating System :: OS Independent
Classifier: Development Status :: 5 - Production/Stable
Classifier: Intended Audience :: Developers
Classifier: Natural Language :: English
Classifier: Topic :: Communications :: Chat
Requires-Python: >=3.11
License-File: LICENSE
Requires-Dist: argparse
Requires-Dist: asyncio
Requires-Dist: async-timeout
Requires-Dist: dbus-python
Requires-Dist: emoji
Requires-Dist: markdown
Requires-Dist: PyGObject
Requires-Dist: uuid
